prngtest.py
prngtest-0.0.1.dist-info/LICENSE
prngtest-0.0.1.dist-info/WHEEL
prngtest-0.0.1.dist-info/METADATA
prngtest-0.0.1.dist-info/RECORD
